{
  "best_metric": null,
  "best_model_checkpoint": null,
  "epoch": 0.7572227399813607,
  "eval_steps": 500,
  "global_step": 6500,
  "is_hyper_param_search": false,
  "is_local_process_zero": true,
  "is_world_process_zero": true,
  "log_history": [
    {
      "epoch": 0.06,
      "learning_rate": 4.902920161540851e-05,
      "loss": 0.7118,
      "step": 500
    },
    {
      "epoch": 0.12,
      "learning_rate": 4.805840323081703e-05,
      "loss": 0.543,
      "step": 1000
    },
    {
      "epoch": 0.17,
      "learning_rate": 4.708760484622554e-05,
      "loss": 0.5066,
      "step": 1500
    },
    {
      "epoch": 0.23,
      "learning_rate": 4.611680646163405e-05,
      "loss": 0.4815,
      "step": 2000
    },
    {
      "epoch": 0.29,
      "learning_rate": 4.514600807704256e-05,
      "loss": 0.4688,
      "step": 2500
    },
    {
      "epoch": 0.35,
      "learning_rate": 4.4175209692451076e-05,
      "loss": 0.4533,
      "step": 3000
    },
    {
      "epoch": 0.41,
      "learning_rate": 4.3204411307859586e-05,
      "loss": 0.4482,
      "step": 3500
    },
    {
      "epoch": 0.47,
      "learning_rate": 4.2233612923268096e-05,
      "loss": 0.4343,
      "step": 4000
    },
    {
      "epoch": 0.52,
      "learning_rate": 4.1262814538676606e-05,
      "loss": 0.4285,
      "step": 4500
    },
    {
      "epoch": 0.58,
      "learning_rate": 4.029201615408512e-05,
      "loss": 0.4172,
      "step": 5000
    },
    {
      "epoch": 0.64,
      "learning_rate": 3.932121776949363e-05,
      "loss": 0.404,
      "step": 5500
    },
    {
      "epoch": 0.7,
      "learning_rate": 3.835041938490215e-05,
      "loss": 0.403,
      "step": 6000
    },
    {
      "epoch": 0.76,
      "learning_rate": 3.737962100031065e-05,
      "loss": 0.4062,
      "step": 6500
    }
  ],
  "logging_steps": 500,
  "max_steps": 25752,
  "num_train_epochs": 3,
  "save_steps": 500,
  "total_flos": 3059724754944000.0,
  "trial_name": null,
  "trial_params": null
}
